fundamental_data/__init__.py
fundamental_data/client.py
fundamental_data/model.py
fundamental_data-0.1.7.dist-info/licenses/LICENSE
fundamental_data-0.1.7.dist-info/METADATA
fundamental_data-0.1.7.dist-info/WHEEL
fundamental_data-0.1.7.dist-info/top_level.txt
fundamental_data-0.1.7.dist-info/RECORD
