Metadata-Version: 2.4
Name: fundamental-data
Version: 0.1.7
Summary: Add your description here
Home-page: https://github.com/mashroor10/fundamental_data/tree/main
Author: Mashroor Rahman
Requires-Python: >=3.10
License-File: LICENSE
Requires-Dist: nbformat>=5.10.4
Requires-Dist: plotly>=6.1.2
Requires-Dist: setuptools>=78.1.0
Requires-Dist: twine>=6.1.0
Requires-Dist: ipykernel>=6.29.5
Requires-Dist: matplotlib>=3.10.1
Requires-Dist: openpyxl>=3.1.5
Requires-Dist: pandas>=2.2.3
Requires-Dist: requests>=2.32.3
Requires-Dist: seaborn>=0.13.2
Requires-Dist: yfinance>=0.2.55
Dynamic: author
Dynamic: home-page
Dynamic: license-file
